betabottle/__init__.py
betabottle-0.0.1.dist-info/licenses/LICENSE
betabottle-0.0.1.dist-info/METADATA
betabottle-0.0.1.dist-info/WHEEL
betabottle-0.0.1.dist-info/top_level.txt
betabottle-0.0.1.dist-info/RECORD
