Metadata-Version: 2.4
Name: betabottle
Version: 0.0.1
Summary: β*-Optimization Validation in the Information Bottleneck Framework
Author-email: Faruk Alpay <alpay@lightcap.ai>
License: MIT
Classifier: Programming Language :: Python :: 3
Classifier: License :: OSI Approved :: MIT License
Classifier: Operating System :: OS Independent
Requires-Python: >=3.8
License-File: LICENSE
Dynamic: license-file
